littlebluefox/__init__.py
littlebluefox_python-1.0.2.dist-info/METADATA
littlebluefox_python-1.0.2.dist-info/WHEEL
littlebluefox_python-1.0.2.dist-info/top_level.txt
littlebluefox_python-1.0.2.dist-info/RECORD
