Metadata-Version: 2.1
Name: littlebluefox-python
Version: 1.0.2
Summary: Official python client for LittleBlueFox.io API
Home-page: https://github.com/littlebluefox/littlebluefox-python
Author: Sam
Author-email: sam@littlebluefox.io
License: UNKNOWN
Platform: UNKNOWN
Classifier: Programming Language :: Python :: 3
Classifier: License :: OSI Approved :: MIT License
Classifier: Operating System :: OS Independent
